fastapi_di_chain/__init__.py
fastapi_di_chain/_chained_dependency_classes.py
fastapi_di_chain/chain.py
fastapi_di_chain/chained_dependency_classes.py
fastapi_di_chain/utils.py
fastapi_di_chain-0.0.5.dist-info/METADATA
fastapi_di_chain-0.0.5.dist-info/WHEEL
fastapi_di_chain-0.0.5.dist-info/licenses/LICENSE
fastapi_di_chain-0.0.5.dist-info/RECORD
