Metadata-Version: 2.4
Name: fastapi-di-chain
Version: 0.0.5
Summary: Chain FastAPI dependencies without unused Depends!
Project-URL: funding, https://github.com/sponsors/aleksul
Project-URL: repository, https://github.com/aleksul/fastapi-di-chain
Author-email: aleksul <me@aleksul.space>
License-File: LICENSE
Classifier: Development Status :: 4 - Beta
Classifier: License :: OSI Approved :: MIT License
Classifier: Programming Language :: Python :: 3
Classifier: Programming Language :: Python :: 3.10
Classifier: Programming Language :: Python :: 3.11
Classifier: Programming Language :: Python :: 3.12
Classifier: Programming Language :: Python :: 3.13
Classifier: Programming Language :: Python :: Implementation :: CPython
Classifier: Typing :: Typed
Requires-Python: >=3.10
Requires-Dist: fastapi>=0.115.14
